MANIFEST.in
README.rst
setup.cfg
setup.py
docs/HISTORY.txt
docs/layout.css
docs/layout.html
src/collective/__init__.py
src/collective.siteisolation.egg-info/PKG-INFO
src/collective.siteisolation.egg-info/SOURCES.txt
src/collective.siteisolation.egg-info/dependency_links.txt
src/collective.siteisolation.egg-info/namespace_packages.txt
src/collective.siteisolation.egg-info/not-zip-safe
src/collective.siteisolation.egg-info/requires.txt
src/collective.siteisolation.egg-info/top_level.txt
src/collective/siteisolation/__init__.py
src/collective/siteisolation/changelog.txt
src/collective/siteisolation/configure.zcml
src/collective/siteisolation/doctest.txt
src/collective/siteisolation/index.txt
src/collective/siteisolation/interfaces.py
src/collective/siteisolation/introduction.txt
src/collective/siteisolation/traverser.py
src/collective/siteisolation/tests/__init__.py
src/collective/siteisolation/tests/test_doctest.py
src/collective/siteisolation/tests/traverser.txt