Metadata-Version: 1.1
Name: collective.siteisolation
Version: 0.2
Summary: Isolate objects in a Zope root from each other
Home-page: http://svn.plone.org/svn/collective/collective.siteisolation
Author: ICTS KULeuven
Author-email: jfroche@affinitic.be
License: GPL
Platform: UNKNOWN
Classifier: Programming Language :: Python
Classifier: Programming Language :: Python :: 2.6
Classifier: Programming Language :: Python :: 2.7
Classifier: Framework :: Plone
Classifier: Framework :: Plone :: 4.1
Classifier: Framework :: Plone :: 4.3
